kwarray/__init__.py
kwarray/algo_assignment.py
kwarray/algo_assignment.pyi
kwarray/algo_setcover.py
kwarray/algo_setcover.pyi
kwarray/arrayapi.py
kwarray/arrayapi.pyi
kwarray/dataframe_light.py
kwarray/dataframe_light.pyi
kwarray/distributions.py
kwarray/distributions.pyi
kwarray/fast_rand.py
kwarray/fast_rand.pyi
kwarray/py.typed
kwarray/util_averages.py
kwarray/util_averages.pyi
kwarray/util_groups.py
kwarray/util_groups.pyi
kwarray/util_misc.py
kwarray/util_misc.pyi
kwarray/util_numpy.py
kwarray/util_numpy.pyi
kwarray/util_random.py
kwarray/util_random.pyi
kwarray/util_robust.py
kwarray/util_robust.pyi
kwarray/util_slices.py
kwarray/util_slices.pyi
kwarray/util_slider.py
kwarray/util_slider.pyi
kwarray/util_torch.py
kwarray/util_torch.pyi
kwarray-0.7.1.dist-info/LICENSE
kwarray-0.7.1.dist-info/METADATA
kwarray-0.7.1.dist-info/WHEEL
kwarray-0.7.1.dist-info/top_level.txt
kwarray-0.7.1.dist-info/RECORD
